telium/__init__.py
telium/main.py
telium/commands/__init__.py
telium/commands/address_book.py
telium/commands/completer.py
telium/commands/handle.py
telium/commands/notes.py
telium/commands/root.py
telium/data/__init__.py
telium/data/data_manager.py
telium/decorators/__init__.py
telium/decorators/command_register.py
telium/decorators/input_error.py
telium/dtos/__init__.py
telium/dtos/address.py
telium/dtos/base.py
telium/dtos/birthday.py
telium/dtos/email.py
telium/dtos/name.py
telium/dtos/phone.py
telium/models/__init__.py
telium/models/note.py
telium/models/record.py
telium/services/__init__.py
telium/services/address_book.py
telium/services/notes.py
telium/utils/__init__.py
telium/utils/constants.py
telium/utils/utils.py
telium/views/__init__.py
telium/views/contact_table.py
telium/views/error.py
telium/views/notes_table.py
telium/views/skip.py
telium/views/success.py
telium-0.2.0.dist-info/METADATA
telium-0.2.0.dist-info/WHEEL
telium-0.2.0.dist-info/entry_points.txt
telium-0.2.0.dist-info/licenses/LICENSE
telium-0.2.0.dist-info/RECORD
